CMakeCache.txt
mix_deploy.cpython-37m-x86_64-linux-gnu.so
mix_stc_infer/__init__.py
mix_stc_infer/commit_id.txt
mix_stc_infer/run.py
mix_deploy-1.4.0.dist-info/METADATA
mix_deploy-1.4.0.dist-info/WHEEL
mix_deploy-1.4.0.dist-info/top_level.txt
mix_deploy-1.4.0.dist-info/RECORD
